{
  "languageserver": {
    "go": {
      "command": "gopls",
      "rootPatterns": ["go.mod"],
      "trace.server": "verbose",
      "filetypes": ["go"]
    }
  },
   "coc.preferences.formatOnSaveFiletypes": [
    "javascript",
    "javascriptreact",
    "typescript",
    "typescriptreact"
  ],
  "prettier.disableSuccessMessage": true,
  "tsserver.formatOnType": true,
  "coc.preferences.formatOnType": true,
  "eslint.autoFixOnSave": true,
  "eslint.filetypes": ["javascript", "javascriptreact", "typescript", "typescriptreact"]
}
